[
  {
    "title": "Autenticación y autorización de usuarios usando JWT",
    "description": "Una API minima para hacer un CRUD de usuarios mediante mecanismos de autenticación y autorización usando JWT.",
    "url": "https://github.com/adanSmith01/UserAuthAndAuthenticationJWT"
  },
  {
    "title": "Generador de códigos QR",
    "description": "Aplicación de consola para crear imágenes de códigos QR personalizados a nivel básico.",
    "url": "https://github.com/adanSmith01/QRCodeGenerator"
  },
  {
    "title": "Sistema Kanban",
    "description": "Proyecto académico de un sistema de gestion de tareas basado en la metodología ágil KANBAN",
    "url": "https://github.com/TallerDeLenguajes1/tl2-tp10-2023-adanSmith01"
  }
]
